setup.py
src/yafowil/__init__.py
src/yafowil.documentation.egg-info/PKG-INFO
src/yafowil.documentation.egg-info/SOURCES.txt
src/yafowil.documentation.egg-info/dependency_links.txt
src/yafowil.documentation.egg-info/namespace_packages.txt
src/yafowil.documentation.egg-info/requires.txt
src/yafowil.documentation.egg-info/top_level.txt
src/yafowil.documentation.egg-info/zip-safe
src/yafowil/documentation/__init__.py
src/yafowil/documentation/sphinxext.py