Metadata-Version: 1.1
Name: yafowil.documentation
Version: 2.1
Summary: Documentation of YAFOWIL - Yet Another Form Widget Library
Home-page: https://github.com/bluedynamics/yafowil
Author: BlueDynamics Alliance
Author-email: dev@bluedynamics.com
License: BSD simplified and CC-BY-SA
Keywords: html input widgets form compound
Platform: UNKNOWN
Classifier: Development Status :: 5 - Production/Stable
Classifier: License :: OSI Approved :: Python Software Foundation License
Classifier: Operating System :: OS Independent
Classifier: Programming Language :: Python
Classifier: Topic :: Software Development
